Metadata-Version: 2.1
Name: facturapi-2.0
Version: 0.0.9.7
Summary: Facturapi API Client V2
Author: KEA Development
Author-email: itservices@kea.mx
License: MIT
Classifier: Programming Language :: Python :: 3
Classifier: Programming Language :: Python :: 3.6
Classifier: Programming Language :: Python :: 3.7
Classifier: Programming Language :: Python :: 3.8
Classifier: License :: OSI Approved :: MIT License
Classifier: Operating System :: OS Independent
Requires-Python: >=3.6
License-File: LICENSE
Requires-Dist: requests<2.26,>=2.4
Requires-Dist: pydantic==1.8.2
Requires-Dist: dataclasses>=0.7; python_version < "3.7"
